{"v":"5.12.2","fr":30,"ip":0,"op":56,"w":512,"h":512,"nm":"Delete_Bin_Paper_lottie","ddd":0,"assets":[],"layers":[{"ddd":0,"ind":1,"ty":4,"nm":"Layer 3 Outlines 2","sr":1,"ks":{"o":{"a":1,"k":[{"i":{"x":[0.19],"y":[1]},"o":{"x":[0.81],"y":[0]},"t":12.2,"s":[100]},{"i":{"x":[0.19],"y":[1]},"o":{"x":[0.81],"y":[0]},"t":23.68,"s":[0]},{"i":{"x":[0.19],"y":[1]},"o":{"x":[0.81],"y":[0]},"t":33.52,"s":[0]},{"t":45,"s":[100]}],"ix":11},"r":{"a":1,"k":[{"i":{"x":[0.19],"y":[1]},"o":{"x":[0.81],"y":[0]},"t":4,"s":[0]},{"i":{"x":[0.19],"y":[1]},"o":{"x":[0.81],"y":[0]},"t":23.68,"s":[122]},{"i":{"x":[0.19],"y":[1]},"o":{"x":[0.81],"y":[0]},"t":25.32,"s":[122]},{"t":45,"s":[0]}],"ix":10},"p":{"a":0,"k":[130,369,0],"ix":2,"l":2},"a":{"a":0,"k":[32.25,32.25,0],"ix":1,"l":2},"s":{"a":1,"k":[{"i":{"x":[0.19,0.19,0.19],"y":[1,1,1]},"o":{"x":[0.81,0.81,0.81],"y":[0,0,0]},"t":9.74,"s":[100,100,100]},{"i":{"x":[0.19,0.19,0.19],"y":[1,1,1]},"o":{"x":[0.81,0.81,0.81],"y":[0,0,0]},"t":23.68,"s":[0,0,100]},{"i":{"x":[0.19,0.19,0.19],"y":[1,1,1]},"o":{"x":[0.81,0.81,0.81],"y":[0,0,0]},"t":31.06,"s":[0,0,100]},{"t":45,"s":[100,100,100]}],"ix":6,"l":2}},"ao":0,"shapes":[{"ty":"gr","it":[{"ind":0,"ty":"sh","ix":1,"ks":{"a":0,"k":{"i":[[0,0],[-0.356,0],[-0.072,0.349],[0,0],[0,0],[0,0.356],[0.349,0.072],[0,0],[0,0],[0.356,0],[0.072,-0.349],[0,0],[0,0],[0,-0.356],[-0.349,-0.072],[0,0]],"o":[[0.072,0.349],[0.356,0],[0,0],[0,0],[0.349,-0.072],[0,-0.356],[0,0],[0,0],[-0.072,-0.349],[-0.356,0],[0,0],[0,0],[-0.349,0.072],[0,0.356],[0,0],[0,0]],"v":[[-0.735,30.15],[0,30.75],[0.735,30.15],[5.732,5.732],[30.15,0.735],[30.75,0],[30.15,-0.735],[5.732,-5.732],[0.735,-30.15],[0,-30.75],[-0.735,-30.15],[-5.732,-5.732],[-30.15,-0.735],[-30.75,0],[-30.15,0.735],[-5.732,5.732]],"c":true},"ix":2},"nm":"Path 1","mn":"ADBE Vector Shape - Group","hd":false},{"ty":"st","c":{"a":0,"k":[0,0,0,1],"ix":3},"o":{"a":0,"k":100,"ix":4},"w":{"a":0,"k":1.5,"ix":5},"lc":1,"lj":2,"bm":0,"nm":"Stroke 1","mn":"ADBE Vector Graphic - Stroke","hd":false},{"ty":"fl","c":{"a":0,"k":[1,1,1,1],"ix":4},"o":{"a":0,"k":100,"ix":5},"r":1,"bm":0,"nm":"Fill 1","mn":"ADBE Vector Graphic - Fill","hd":false},{"ty":"tr","p":{"a":0,"k":[32.25,32.25],"ix":2},"a":{"a":0,"k":[0,0],"ix":1},"s":{"a":0,"k":[100,100],"ix":3},"r":{"a":0,"k":0,"ix":6},"o":{"a":0,"k":100,"ix":7},"sk":{"a":0,"k":0,"ix":4},"sa":{"a":0,"k":0,"ix":5},"nm":"Transform"}],"nm":"Group 1","np":3,"cix":2,"bm":0,"ix":1,"mn":"ADBE Vector Group","hd":false}],"ip":0,"op":152,"st":0,"ct":1,"bm":0},{"ddd":0,"ind":2,"ty":4,"nm":"Layer 2 Outlines 2","sr":1,"ks":{"o":{"a":1,"k":[{"i":{"x":[0.19],"y":[1]},"o":{"x":[0.81],"y":[0]},"t":12.2,"s":[100]},{"i":{"x":[0.19],"y":[1]},"o":{"x":[0.81],"y":[0]},"t":23.68,"s":[0]},{"i":{"x":[0.19],"y":[1]},"o":{"x":[0.81],"y":[0]},"t":33.52,"s":[0]},{"t":45,"s":[100]}],"ix":11},"r":{"a":1,"k":[{"i":{"x":[0.19],"y":[1]},"o":{"x":[0.81],"y":[0]},"t":4,"s":[0]},{"i":{"x":[0.19],"y":[1]},"o":{"x":[0.81],"y":[0]},"t":23.68,"s":[125]},{"i":{"x":[0.19],"y":[1]},"o":{"x":[0.81],"y":[0]},"t":25.32,"s":[125]},{"t":45,"s":[0]}],"ix":10},"p":{"a":0,"k":[408.5,131.5,0],"ix":2,"l":2},"a":{"a":0,"k":[29.75,29.75,0],"ix":1,"l":2},"s":{"a":1,"k":[{"i":{"x":[0.19,0.19,0.19],"y":[1,1,1]},"o":{"x":[0.81,0.81,0.81],"y":[0,0,0]},"t":9.74,"s":[100,100,100]},{"i":{"x":[0.19,0.19,0.19],"y":[1,1,1]},"o":{"x":[0.81,0.81,0.81],"y":[0,0,0]},"t":23.68,"s":[0,0,100]},{"i":{"x":[0.19,0.19,0.19],"y":[1,1,1]},"o":{"x":[0.81,0.81,0.81],"y":[0,0,0]},"t":31.06,"s":[0,0,100]},{"t":45,"s":[100,100,100]}],"ix":6,"l":2}},"ao":0,"shapes":[{"ty":"gr","it":[{"ind":0,"ty":"sh","ix":1,"ks":{"a":0,"k":{"i":[[0,0],[-0.356,0],[-0.072,0.349],[0,0],[0,0],[0,0.356],[0.349,0.072],[0,0],[0,0],[0.356,0],[0.072,-0.349],[0,0],[0,0],[0,-0.356],[-0.349,-0.072],[0,0]],"o":[[0.072,0.349],[0.356,0],[0,0],[0,0],[0.349,-0.072],[0,-0.356],[0,0],[0,0],[-0.072,-0.349],[-0.356,0],[0,0],[0,0],[-0.349,0.072],[0,0.356],[0,0],[0,0]],"v":[[-0.735,27.65],[0,28.25],[0.735,27.65],[5.307,5.307],[27.65,0.735],[28.25,0],[27.65,-0.735],[5.307,-5.307],[0.735,-27.65],[0,-28.25],[-0.735,-27.65],[-5.307,-5.307],[-27.65,-0.735],[-28.25,0],[-27.65,0.735],[-5.307,5.307]],"c":true},"ix":2},"nm":"Path 1","mn":"ADBE Vector Shape - Group","hd":false},{"ty":"st","c":{"a":0,"k":[0,0,0,1],"ix":3},"o":{"a":0,"k":100,"ix":4},"w":{"a":0,"k":1.5,"ix":5},"lc":1,"lj":2,"bm":0,"nm":"Stroke 1","mn":"ADBE Vector Graphic - Stroke","hd":false},{"ty":"fl","c":{"a":0,"k":[1,1,1,1],"ix":4},"o":{"a":0,"k":100,"ix":5},"r":1,"bm":0,"nm":"Fill 1","mn":"ADBE Vector Graphic - Fill","hd":false},{"ty":"tr","p":{"a":0,"k":[29.75,29.75],"ix":2},"a":{"a":0,"k":[0,0],"ix":1},"s":{"a":0,"k":[100,100],"ix":3},"r":{"a":0,"k":0,"ix":6},"o":{"a":0,"k":100,"ix":7},"sk":{"a":0,"k":0,"ix":4},"sa":{"a":0,"k":0,"ix":5},"nm":"Transform"}],"nm":"Group 1","np":3,"cix":2,"bm":0,"ix":1,"mn":"ADBE Vector Group","hd":false}],"ip":0,"op":152,"st":0,"ct":1,"bm":0},{"ddd":0,"ind":3,"ty":3,"nm":"Null 1","sr":1,"ks":{"o":{"a":0,"k":0,"ix":11},"r":{"a":1,"k":[{"i":{"x":[0.19],"y":[1]},"o":{"x":[0.81],"y":[0]},"t":5,"s":[0]},{"i":{"x":[0.19],"y":[1]},"o":{"x":[0.81],"y":[0]},"t":22,"s":[14]},{"i":{"x":[0.833],"y":[1]},"o":{"x":[0.81],"y":[0]},"t":27,"s":[14]},{"i":{"x":[0.19],"y":[1]},"o":{"x":[0.167],"y":[0]},"t":42,"s":[14]},{"t":50,"s":[0]}],"ix":10},"p":{"a":1,"k":[{"i":{"x":0.19,"y":1},"o":{"x":0.81,"y":0},"t":5,"s":[220.253,132.97,0],"to":[7.417,-12.417,0],"ti":[-7.417,12.417,0]},{"i":{"x":0.19,"y":0.19},"o":{"x":0.81,"y":0.81},"t":22,"s":[264.753,58.47,0],"to":[0,0,0],"ti":[0,0,0]},{"i":{"x":0.19,"y":1},"o":{"x":0.81,"y":0},"t":27,"s":[264.753,58.47,0],"to":[0,30,0],"ti":[0,-17.167,0]},{"i":{"x":0.19,"y":1},"o":{"x":0.81,"y":0},"t":34,"s":[264.753,238.47,0],"to":[0,17.167,0],"ti":[0,12.833,0]},{"i":{"x":0.19,"y":0.19},"o":{"x":0.81,"y":0.81},"t":41,"s":[264.753,161.47,0],"to":[0,0,0],"ti":[0,0,0]},{"i":{"x":0.19,"y":1},"o":{"x":0.81,"y":0},"t":42,"s":[264.753,161.47,0],"to":[-7.417,-4.75,0],"ti":[7.417,4.75,0]},{"t":50,"s":[220.253,132.97,0]}],"ix":2,"l":2},"a":{"a":0,"k":[0,0,0],"ix":1,"l":2},"s":{"a":0,"k":[100,100,100],"ix":6,"l":2}},"ao":0,"ip":0,"op":151,"st":0,"bm":0},{"ddd":0,"ind":4,"ty":4,"nm":"Layer 33 Outlines","parent":3,"sr":1,"ks":{"o":{"a":0,"k":100,"ix":11},"r":{"a":0,"k":0,"ix":10},"p":{"a":0,"k":[8.369,30.222,0],"ix":2,"l":2},"a":{"a":0,"k":[124.684,40.96,0],"ix":1,"l":2},"s":{"a":0,"k":[100,100,100],"ix":6,"l":2}},"ao":0,"shapes":[{"ty":"gr","it":[{"ind":0,"ty":"sh","ix":1,"ks":{"a":0,"k":{"i":[[0,0],[0,0]],"o":[[0,0],[0,0]],"v":[[-1.72,-6.419],[1.72,6.419]],"c":false},"ix":2},"nm":"Path 1","mn":"ADBE Vector Shape - Group","hd":false},{"ty":"st","c":{"a":0,"k":[0,0,0,1],"ix":3},"o":{"a":0,"k":100,"ix":4},"w":{"a":0,"k":1.5,"ix":5},"lc":2,"lj":1,"ml":4,"bm":0,"nm":"Stroke 1","mn":"ADBE Vector Graphic - Stroke","hd":false},{"ty":"tr","p":{"a":0,"k":[246.898,7.169],"ix":2},"a":{"a":0,"k":[0,0],"ix":1},"s":{"a":0,"k":[100,100],"ix":3},"r":{"a":0,"k":0,"ix":6},"o":{"a":0,"k":100,"ix":7},"sk":{"a":0,"k":0,"ix":4},"sa":{"a":0,"k":0,"ix":5},"nm":"Transform"}],"nm":"Group 1","np":2,"cix":2,"bm":0,"ix":1,"mn":"ADBE Vector Group","hd":false},{"ty":"gr","it":[{"ind":0,"ty":"sh","ix":1,"ks":{"a":0,"k":{"i":[[0,0],[0,0]],"o":[[0,0],[0,0]],"v":[[-1.719,-6.419],[1.719,6.419]],"c":false},"ix":2},"nm":"Path 1","mn":"ADBE Vector Shape - Group","hd":false},{"ty":"st","c":{"a":0,"k":[0,0,0,1],"ix":3},"o":{"a":0,"k":100,"ix":4},"w":{"a":0,"k":1.5,"ix":5},"lc":2,"lj":1,"ml":4,"bm":0,"nm":"Stroke 1","mn":"ADBE Vector Graphic - Stroke","hd":false},{"ty":"tr","p":{"a":0,"k":[2.47,72.663],"ix":2},"a":{"a":0,"k":[0,0],"ix":1},"s":{"a":0,"k":[100,100],"ix":3},"r":{"a":0,"k":0,"ix":6},"o":{"a":0,"k":100,"ix":7},"sk":{"a":0,"k":0,"ix":4},"sa":{"a":0,"k":0,"ix":5},"nm":"Transform"}],"nm":"Group 2","np":2,"cix":2,"bm":0,"ix":2,"mn":"ADBE Vector Group","hd":false},{"ty":"gr","it":[{"ind":0,"ty":"sh","ix":1,"ks":{"a":0,"k":{"i":[[0,0],[0,0]],"o":[[0,0],[0,0]],"v":[[-1.719,-6.419],[1.719,6.419]],"c":false},"ix":2},"nm":"Path 1","mn":"ADBE Vector Shape - Group","hd":false},{"ty":"st","c":{"a":0,"k":[0,0,0,1],"ix":3},"o":{"a":0,"k":100,"ix":4},"w":{"a":0,"k":1.5,"ix":5},"lc":2,"lj":1,"ml":4,"bm":0,"nm":"Stroke 1","mn":"ADBE Vector Graphic - Stroke","hd":false},{"ty":"tr","p":{"a":0,"k":[222.672,23.567],"ix":2},"a":{"a":0,"k":[0,0],"ix":1},"s":{"a":0,"k":[100,100],"ix":3},"r":{"a":0,"k":0,"ix":6},"o":{"a":0,"k":100,"ix":7},"sk":{"a":0,"k":0,"ix":4},"sa":{"a":0,"k":0,"ix":5},"nm":"Transform"}],"nm":"Group 3","np":2,"cix":2,"bm":0,"ix":3,"mn":"ADBE Vector Group","hd":false},{"ty":"gr","it":[{"ind":0,"ty":"sh","ix":1,"ks":{"a":0,"k":{"i":[[0,0],[0,0]],"o":[[0,0],[0,0]],"v":[[-1.72,-6.419],[1.72,6.419]],"c":false},"ix":2},"nm":"Path 1","mn":"ADBE Vector Shape - Group","hd":false},{"ty":"st","c":{"a":0,"k":[0,0,0,1],"ix":3},"o":{"a":0,"k":100,"ix":4},"w":{"a":0,"k":1.5,"ix":5},"lc":2,"lj":1,"ml":4,"bm":0,"nm":"Stroke 1","mn":"ADBE Vector Graphic - Stroke","hd":false},{"ty":"tr","p":{"a":0,"k":[31.649,74.752],"ix":2},"a":{"a":0,"k":[0,0],"ix":1},"s":{"a":0,"k":[100,100],"ix":3},"r":{"a":0,"k":0,"ix":6},"o":{"a":0,"k":100,"ix":7},"sk":{"a":0,"k":0,"ix":4},"sa":{"a":0,"k":0,"ix":5},"nm":"Transform"}],"nm":"Group 4","np":2,"cix":2,"bm":0,"ix":4,"mn":"ADBE Vector Group","hd":false},{"ty":"gr","it":[{"ind":0,"ty":"sh","ix":1,"ks":{"a":0,"k":{"i":[[0,0],[0,0]],"o":[[0,0],[0,0]],"v":[[-1.72,-6.419],[1.72,6.419]],"c":false},"ix":2},"nm":"Path 1","mn":"ADBE Vector Shape - Group","hd":false},{"ty":"st","c":{"a":0,"k":[0,0,0,1],"ix":3},"o":{"a":0,"k":100,"ix":4},"w":{"a":0,"k":1.5,"ix":5},"lc":2,"lj":1,"ml":4,"bm":0,"nm":"Stroke 1","mn":"ADBE Vector Graphic - Stroke","hd":false},{"ty":"tr","p":{"a":0,"k":[195.293,36.407],"ix":2},"a":{"a":0,"k":[0,0],"ix":1},"s":{"a":0,"k":[100,100],"ix":3},"r":{"a":0,"k":0,"ix":6},"o":{"a":0,"k":100,"ix":7},"sk":{"a":0,"k":0,"ix":4},"sa":{"a":0,"k":0,"ix":5},"nm":"Transform"}],"nm":"Group 5","np":2,"cix":2,"bm":0,"ix":5,"mn":"ADBE Vector Group","hd":false},{"ty":"gr","it":[{"ind":0,"ty":"sh","ix":1,"ks":{"a":0,"k":{"i":[[0,0],[0,0]],"o":[[0,0],[0,0]],"v":[[-1.72,-6.419],[1.72,6.419]],"c":false},"ix":2},"nm":"Path 1","mn":"ADBE Vector Shape - Group","hd":false},{"ty":"st","c":{"a":0,"k":[0,0,0,1],"ix":3},"o":{"a":0,"k":100,"ix":4},"w":{"a":0,"k":1.5,"ix":5},"lc":2,"lj":1,"ml":4,"bm":0,"nm":"Stroke 1","mn":"ADBE Vector Graphic - Stroke","hd":false},{"ty":"tr","p":{"a":0,"k":[61.782,72.182],"ix":2},"a":{"a":0,"k":[0,0],"ix":1},"s":{"a":0,"k":[100,100],"ix":3},"r":{"a":0,"k":0,"ix":6},"o":{"a":0,"k":100,"ix":7},"sk":{"a":0,"k":0,"ix":4},"sa":{"a":0,"k":0,"ix":5},"nm":"Transform"}],"nm":"Group 6","np":2,"cix":2,"bm":0,"ix":6,"mn":"ADBE Vector Group","hd":false},{"ty":"gr","it":[{"ind":0,"ty":"sh","ix":1,"ks":{"a":0,"k":{"i":[[0,0],[0,0]],"o":[[0,0],[0,0]],"v":[[-1.72,-6.419],[1.72,6.419]],"c":false},"ix":2},"nm":"Path 1","mn":"ADBE Vector Shape - Group","hd":false},{"ty":"st","c":{"a":0,"k":[0,0,0,1],"ix":3},"o":{"a":0,"k":100,"ix":4},"w":{"a":0,"k":1.5,"ix":5},"lc":2,"lj":1,"ml":4,"bm":0,"nm":"Stroke 1","mn":"ADBE Vector Graphic - Stroke","hd":false},{"ty":"tr","p":{"a":0,"k":[165.583,48.771],"ix":2},"a":{"a":0,"k":[0,0],"ix":1},"s":{"a":0,"k":[100,100],"ix":3},"r":{"a":0,"k":0,"ix":6},"o":{"a":0,"k":100,"ix":7},"sk":{"a":0,"k":0,"ix":4},"sa":{"a":0,"k":0,"ix":5},"nm":"Transform"}],"nm":"Group 7","np":2,"cix":2,"bm":0,"ix":7,"mn":"ADBE Vector Group","hd":false},{"ty":"gr","it":[{"ind":0,"ty":"sh","ix":1,"ks":{"a":0,"k":{"i":[[0,0],[0,0]],"o":[[0,0],[0,0]],"v":[[-1.72,-6.419],[1.72,6.419]],"c":false},"ix":2},"nm":"Path 1","mn":"ADBE Vector Shape - Group","hd":false},{"ty":"st","c":{"a":0,"k":[0,0,0,1],"ix":3},"o":{"a":0,"k":100,"ix":4},"w":{"a":0,"k":1.5,"ix":5},"lc":2,"lj":1,"ml":4,"bm":0,"nm":"Stroke 1","mn":"ADBE Vector Graphic - Stroke","hd":false},{"ty":"tr","p":{"a":0,"k":[93.692,68.034],"ix":2},"a":{"a":0,"k":[0,0],"ix":1},"s":{"a":0,"k":[100,100],"ix":3},"r":{"a":0,"k":0,"ix":6},"o":{"a":0,"k":100,"ix":7},"sk":{"a":0,"k":0,"ix":4},"sa":{"a":0,"k":0,"ix":5},"nm":"Transform"}],"nm":"Group 8","np":2,"cix":2,"bm":0,"ix":8,"mn":"ADBE Vector Group","hd":false},{"ty":"gr","it":[{"ind":0,"ty":"sh","ix":1,"ks":{"a":0,"k":{"i":[[0,0],[0,0]],"o":[[0,0],[0,0]],"v":[[-1.72,-6.419],[1.72,6.419]],"c":false},"ix":2},"nm":"Path 1","mn":"ADBE Vector Shape - Group","hd":false},{"ty":"st","c":{"a":0,"k":[0,0,0,1],"ix":3},"o":{"a":0,"k":100,"ix":4},"w":{"a":0,"k":1.5,"ix":5},"lc":2,"lj":1,"ml":4,"bm":0,"nm":"Stroke 1","mn":"ADBE Vector Graphic - Stroke","hd":false},{"ty":"tr","p":{"a":0,"k":[129.637,58.402],"ix":2},"a":{"a":0,"k":[0,0],"ix":1},"s":{"a":0,"k":[100,100],"ix":3},"r":{"a":0,"k":0,"ix":6},"o":{"a":0,"k":100,"ix":7},"sk":{"a":0,"k":0,"ix":4},"sa":{"a":0,"k":0,"ix":5},"nm":"Transform"}],"nm":"Group 9","np":2,"cix":2,"bm":0,"ix":9,"mn":"ADBE Vector Group","hd":false}],"ip":0,"op":151,"st":0,"ct":1,"bm":0},{"ddd":0,"ind":5,"ty":4,"nm":"Layer 13 Outlines","parent":3,"sr":1,"ks":{"o":{"a":0,"k":100,"ix":11},"r":{"a":0,"k":0,"ix":10},"p":{"a":0,"k":[-1.431,-5.346,0],"ix":2,"l":2},"a":{"a":0,"k":[20.808,7.248,0],"ix":1,"l":2},"s":{"a":0,"k":[100,100,100],"ix":6,"l":2}},"ao":0,"shapes":[{"ty":"gr","it":[{"ind":0,"ty":"sh","ix":1,"ks":{"a":0,"k":{"i":[[0.001,0.002],[0,0]],"o":[[0.001,0.002],[0,0]],"v":[[19.306,-5.16],[19.308,-5.158]],"c":true},"ix":2},"nm":"Path 1","mn":"ADBE Vector Shape - Group","hd":false},{"ind":1,"ty":"sh","ix":2,"ks":{"a":0,"k":{"i":[[0,0],[0,0]],"o":[[0,0],[0,0]],"v":[[-19.3,5.187],[-19.3,5.184]],"c":true},"ix":2},"nm":"Path 2","mn":"ADBE Vector Shape - Group","hd":false},{"ind":2,"ty":"sh","ix":3,"ks":{"a":0,"k":{"i":[[0,0],[-0.001,-0.002]],"o":[[0,0],[-0.001,-0.001]],"v":[[-19.308,5.158],[-19.306,5.16]],"c":true},"ix":2},"nm":"Path 3","mn":"ADBE Vector Shape - Group","hd":false},{"ind":3,"ty":"sh","ix":4,"ks":{"a":0,"k":{"i":[[-0.228,-0.112],[-0.019,-0.023],[0.082,-0.123],[0.419,-0.328],[1.705,-0.802],[5.501,-1.474],[3.742,-0.316],[1.048,0.147],[0.228,0.112],[0.019,0.023],[-0.082,0.123],[-0.42,0.328],[-1.705,0.802],[-5.501,1.474],[-3.742,0.316],[-1.048,-0.147]],"o":[[0.132,0.065],[-0.005,0.029],[-0.141,0.211],[-0.834,0.651],[-3.399,1.597],[-5.501,1.474],[-1.877,0.158],[-0.527,-0.074],[-0.132,-0.065],[0.005,-0.029],[0.141,-0.211],[0.833,-0.651],[3.399,-1.597],[5.501,-1.474],[1.877,-0.158],[0.527,0.074]],"v":[[19.094,-5.309],[19.298,-5.171],[19.19,-4.949],[18.366,-4.136],[14.523,-1.931],[0.769,2.87],[-13.543,5.589],[-17.974,5.601],[-19.094,5.309],[-19.298,5.171],[-19.19,4.949],[-18.366,4.136],[-14.523,1.931],[-0.769,-2.87],[13.543,-5.589],[17.974,-5.601]],"c":true},"ix":2},"nm":"Path 4","mn":"ADBE Vector Shape - Group","hd":false},{"ind":4,"ty":"sh","ix":5,"ks":{"a":0,"k":{"i":[[0,0],[0,0]],"o":[[0,0],[0,0]],"v":[[19.3,-5.187],[19.3,-5.184]],"c":true},"ix":2},"nm":"Path 5","mn":"ADBE Vector Shape - Group","hd":false},{"ty":"mm","mm":1,"nm":"Merge Paths 1","mn":"ADBE Vector Filter - Merge","hd":false},{"ty":"st","c":{"a":0,"k":[0,0,0,1],"ix":3},"o":{"a":0,"k":100,"ix":4},"w":{"a":0,"k":1.5,"ix":5},"lc":1,"lj":1,"ml":4,"bm":0,"nm":"Stroke 1","mn":"ADBE Vector Graphic - Stroke","hd":false},{"ty":"fl","c":{"a":0,"k":[0.058823533152,1,0.141176470588,1],"ix":4},"o":{"a":0,"k":100,"ix":5},"r":1,"bm":0,"nm":"Fill 1","mn":"ADBE Vector Graphic - Fill","hd":false},{"ty":"tr","p":{"a":0,"k":[20.808,7.248],"ix":2},"a":{"a":0,"k":[0,0],"ix":1},"s":{"a":0,"k":[100,100],"ix":3},"r":{"a":0,"k":0,"ix":6},"o":{"a":0,"k":100,"ix":7},"sk":{"a":0,"k":0,"ix":4},"sa":{"a":0,"k":0,"ix":5},"nm":"Transform"}],"nm":"Group 1","np":8,"cix":2,"bm":0,"ix":1,"mn":"ADBE Vector Group","hd":false}],"ip":0,"op":151,"st":0,"ct":1,"bm":0},{"ddd":0,"ind":6,"ty":4,"nm":"Layer 15 Outlines","parent":3,"sr":1,"ks":{"o":{"a":0,"k":100,"ix":11},"r":{"a":0,"k":0,"ix":10},"p":{"a":0,"k":[0.356,1.603,0],"ix":2,"l":2},"a":{"a":0,"k":[22.203,13.079,0],"ix":1,"l":2},"s":{"a":0,"k":[100,100,100],"ix":6,"l":2}},"ao":0,"shapes":[{"ty":"gr","it":[{"ind":0,"ty":"sh","ix":1,"ks":{"a":0,"k":{"i":[[0,0],[0,0],[0,0],[0,0],[-1.781,0],[-6.779,1.817],[-1.154,2.212],[0,0],[0,0],[0,0.002],[0.001,0.002]],"o":[[0,0],[0,0],[0,0],[0.662,0.421],[3.884,0],[9.889,-2.649],[0,0],[0,0],[0,-0.002],[-0.001,-0.002],[0,0]],"v":[[18.101,-12.829],[-21.953,-2.096],[-18.1,12.282],[-17.806,12.203],[-14.06,12.829],[2.764,10.041],[21.66,1.628],[21.953,1.55],[21.781,0.908],[21.78,0.902],[21.778,0.896]],"c":true},"ix":2},"nm":"Path 1","mn":"ADBE Vector Shape - Group","hd":false},{"ind":1,"ty":"sh","ix":2,"ks":{"a":0,"k":{"i":[[0,0],[0,0],[10.322,-2.765],[3.897,0],[0.258,0.11],[0,0]],"o":[[0,0],[-0.994,1.451],[-6.395,1.714],[-1.82,0],[0,0],[0,0]],"v":[[17.04,-10.992],[20.264,1.043],[2.376,8.592],[-14.06,11.329],[-16.893,10.991],[-20.116,-1.035]],"c":true},"ix":2},"nm":"Path 2","mn":"ADBE Vector Shape - Group","hd":false},{"ty":"mm","mm":1,"nm":"Merge Paths 1","mn":"ADBE Vector Filter - Merge","hd":false},{"ty":"fl","c":{"a":0,"k":[0,0,0,1],"ix":4},"o":{"a":0,"k":100,"ix":5},"r":1,"bm":0,"nm":"Fill 1","mn":"ADBE Vector Graphic - Fill","hd":false},{"ty":"tr","p":{"a":0,"k":[22.203,13.079],"ix":2},"a":{"a":0,"k":[0,0],"ix":1},"s":{"a":0,"k":[100,100],"ix":3},"r":{"a":0,"k":0,"ix":6},"o":{"a":0,"k":100,"ix":7},"sk":{"a":0,"k":0,"ix":4},"sa":{"a":0,"k":0,"ix":5},"nm":"Transform"}],"nm":"Group 1","np":4,"cix":2,"bm":0,"ix":1,"mn":"ADBE Vector Group","hd":false},{"ty":"gr","it":[{"ind":0,"ty":"sh","ix":1,"ks":{"a":0,"k":{"i":[[0,0],[0.24,0.153],[0.045,0.017],[0,0],[0,0],[0,0],[0.023,-0.043],[10.357,-2.774],[3.958,0]],"o":[[-2.297,0],[-0.041,-0.026],[0,0],[0,0],[0,0],[-0.029,0.037],[-0.924,1.771],[-6.454,1.73],[0,0]],"v":[[-14.079,11.995],[-17.423,11.486],[-17.552,11.421],[-21.054,-1.65],[17.552,-11.995],[21.054,1.078],[20.976,1.198],[2.551,9.232],[-14.077,11.995]],"c":true},"ix":2},"nm":"Path 1","mn":"ADBE Vector Shape - Group","hd":false},{"ty":"fl","c":{"a":0,"k":[0.058823533152,1,0.141176470588,1],"ix":4},"o":{"a":0,"k":100,"ix":5},"r":1,"bm":0,"nm":"Fill 1","mn":"ADBE Vector Graphic - Fill","hd":false},{"ty":"tr","p":{"a":0,"k":[22.222,13.163],"ix":2},"a":{"a":0,"k":[0,0],"ix":1},"s":{"a":0,"k":[100,100],"ix":3},"r":{"a":0,"k":0,"ix":6},"o":{"a":0,"k":100,"ix":7},"sk":{"a":0,"k":0,"ix":4},"sa":{"a":0,"k":0,"ix":5},"nm":"Transform"}],"nm":"Group 2","np":2,"cix":2,"bm":0,"ix":2,"mn":"ADBE Vector Group","hd":false}],"ip":0,"op":151,"st":0,"ct":1,"bm":0},{"ddd":0,"ind":7,"ty":4,"nm":"Layer 17 Outlines","parent":3,"sr":1,"ks":{"o":{"a":0,"k":100,"ix":11},"r":{"a":0,"k":0,"ix":10},"p":{"a":0,"k":[-0.926,-1.842,0],"ix":2,"l":2},"a":{"a":0,"k":[116.826,40.256,0],"ix":1,"l":2},"s":{"a":0,"k":[100,100,100],"ix":6,"l":2}},"ao":0,"shapes":[{"ty":"gr","it":[{"ind":0,"ty":"sh","ix":1,"ks":{"a":0,"k":{"i":[[0.078,-0.609],[0.782,2.916],[63.243,-16.946],[-3.347,-12.493],[-5.772,-1.197],[0.15,0.56],[-59.079,15.83],[-3.069,-11.452]],"o":[[4.401,-3.922],[-3.347,-12.493],[-63.243,16.946],[0.781,2.916],[-0.372,-0.489],[-3.068,-11.452],[59.079,-15.83],[0.15,0.56]],"v":[[110.129,-17.139],[115.794,-27.512],[-4.778,-19.448],[-113.229,33.854],[-103.135,40.005],[-103.921,38.432],[-2.505,-10.966],[110.023,-18.895]],"c":true},"ix":2},"nm":"Path 1","mn":"ADBE Vector Shape - Group","hd":false},{"ty":"fl","c":{"a":0,"k":[0,0,0,1],"ix":4},"o":{"a":0,"k":100,"ix":5},"r":1,"bm":0,"nm":"Fill 1","mn":"ADBE Vector Graphic - Fill","hd":false},{"ty":"tr","p":{"a":0,"k":[116.826,40.256],"ix":2},"a":{"a":0,"k":[0,0],"ix":1},"s":{"a":0,"k":[100,100],"ix":3},"r":{"a":0,"k":0,"ix":6},"o":{"a":0,"k":100,"ix":7},"sk":{"a":0,"k":0,"ix":4},"sa":{"a":0,"k":0,"ix":5},"nm":"Transform"}],"nm":"Group 1","np":2,"cix":2,"bm":0,"ix":1,"mn":"ADBE Vector Group","hd":false}],"ip":0,"op":151,"st":0,"ct":1,"bm":0},{"ddd":0,"ind":8,"ty":4,"nm":"Layer 18 Outlines","parent":3,"sr":1,"ks":{"o":{"a":0,"k":100,"ix":11},"r":{"a":0,"k":0,"ix":10},"p":{"a":0,"k":[0.356,1.329,0],"ix":2,"l":2},"a":{"a":0,"k":[115.633,39.155,0],"ix":1,"l":2},"s":{"a":0,"k":[100,100,100],"ix":6,"l":2}},"ao":0,"shapes":[{"ty":"gr","it":[{"ind":0,"ty":"sh","ix":1,"ks":{"a":0,"k":{"i":[[-0.346,-1.293],[1.071,-1.779],[2.503,-2.101],[9.791,-4.81],[31.589,-8.464],[21.757,-1.46],[6.432,1.136],[1.818,1.006],[0.347,1.293],[-1.071,1.78],[-2.504,2.101],[-9.792,4.81],[-31.589,8.465],[-21.756,1.459],[-6.433,-1.135],[-1.818,-1.006]],"o":[[0.346,1.293],[-1.071,1.78],[-5.003,4.2],[-19.571,9.614],[-31.589,8.464],[-10.884,0.73],[-3.218,-0.568],[-1.817,-1.005],[-0.346,-1.292],[1.072,-1.78],[5.002,-4.199],[19.571,-9.614],[31.589,-8.464],[10.884,-0.731],[3.218,0.568],[1.817,1.006]],"v":[[113.788,-30.489],[112.763,-25.893],[107.388,-20.052],[84.923,-6.393],[5.861,21.87],[-76.742,36.925],[-103.026,36.328],[-110.602,33.957],[-113.788,30.489],[-112.763,25.893],[-107.387,20.052],[-84.922,6.393],[-5.86,-21.87],[76.742,-36.924],[103.027,-36.328],[110.603,-33.957]],"c":true},"ix":2},"nm":"Path 1","mn":"ADBE Vector Shape - Group","hd":false},{"ty":"st","c":{"a":0,"k":[0,0,0,1],"ix":3},"o":{"a":0,"k":100,"ix":4},"w":{"a":0,"k":1.5,"ix":5},"lc":1,"lj":1,"ml":4,"bm":0,"nm":"Stroke 1","mn":"ADBE Vector Graphic - Stroke","hd":false},{"ty":"fl","c":{"a":0,"k":[0.921568687289,1,0,1],"ix":4},"o":{"a":0,"k":100,"ix":5},"r":1,"bm":0,"nm":"Fill 1","mn":"ADBE Vector Graphic - Fill","hd":false},{"ty":"tr","p":{"a":0,"k":[115.634,39.155],"ix":2},"a":{"a":0,"k":[0,0],"ix":1},"s":{"a":0,"k":[100,100],"ix":3},"r":{"a":0,"k":0,"ix":6},"o":{"a":0,"k":100,"ix":7},"sk":{"a":0,"k":0,"ix":4},"sa":{"a":0,"k":0,"ix":5},"nm":"Transform"}],"nm":"Group 1","np":3,"cix":2,"bm":0,"ix":1,"mn":"ADBE Vector Group","hd":false}],"ip":0,"op":151,"st":0,"ct":1,"bm":0},{"ddd":0,"ind":9,"ty":4,"nm":"Layer 19 Outlines","parent":3,"sr":1,"ks":{"o":{"a":0,"k":100,"ix":11},"r":{"a":0,"k":0,"ix":10},"p":{"a":0,"k":[0.356,1.33,0],"ix":2,"l":2},"a":{"a":0,"k":[137.383,49.464,0],"ix":1,"l":2},"s":{"a":0,"k":[100,100,100],"ix":6,"l":2}},"ao":0,"shapes":[{"ty":"gr","it":[{"ind":0,"ty":"sh","ix":1,"ks":{"a":0,"k":{"i":[[-0.529,-1.974],[1.203,-2.447],[2.897,-2.793],[11.514,-6.166],[37.539,-10.058],[26.096,-0.835],[7.81,1.94],[2.27,1.521],[0.529,1.974],[-1.202,2.447],[-2.898,2.793],[-11.514,6.166],[-37.539,10.058],[-26.097,0.834],[-7.81,-1.94],[-2.27,-1.521]],"o":[[0.529,1.975],[-1.205,2.452],[-5.794,5.585],[-23.017,12.326],[-37.538,10.059],[-13.055,0.418],[-3.905,-0.97],[-2.264,-1.517],[-0.529,-1.975],[1.206,-2.452],[5.793,-5.585],[23.018,-12.325],[37.539,-10.059],[13.054,-0.418],[3.906,0.97],[2.265,1.518]],"v":[[135.354,-36.268],[134.361,-29.635],[128.185,-21.745],[101.9,-3.931],[8.337,31.113],[-90.213,47.546],[-121.883,45.262],[-131.178,41.514],[-135.355,36.269],[-134.36,29.635],[-128.184,21.745],[-101.9,3.932],[-8.336,-31.112],[90.214,-47.546],[121.883,-45.262],[131.177,-41.516]],"c":true},"ix":2},"nm":"Path 1","mn":"ADBE Vector Shape - Group","hd":false},{"ty":"st","c":{"a":0,"k":[0,0,0,1],"ix":3},"o":{"a":0,"k":100,"ix":4},"w":{"a":0,"k":1.5,"ix":5},"lc":1,"lj":1,"ml":4,"bm":0,"nm":"Stroke 1","mn":"ADBE Vector Graphic - Stroke","hd":false},{"ty":"fl","c":{"a":0,"k":[0.921568687289,1,0,1],"ix":4},"o":{"a":0,"k":100,"ix":5},"r":1,"bm":0,"nm":"Fill 1","mn":"ADBE Vector Graphic - Fill","hd":false},{"ty":"tr","p":{"a":0,"k":[137.383,49.464],"ix":2},"a":{"a":0,"k":[0,0],"ix":1},"s":{"a":0,"k":[100,100],"ix":3},"r":{"a":0,"k":0,"ix":6},"o":{"a":0,"k":100,"ix":7},"sk":{"a":0,"k":0,"ix":4},"sa":{"a":0,"k":0,"ix":5},"nm":"Transform"}],"nm":"Group 1","np":3,"cix":2,"bm":0,"ix":1,"mn":"ADBE Vector Group","hd":false}],"ip":0,"op":151,"st":0,"ct":1,"bm":0},{"ddd":0,"ind":10,"ty":4,"nm":"Layer 21 Outlines","parent":3,"sr":1,"ks":{"o":{"a":0,"k":100,"ix":11},"r":{"a":0,"k":0,"ix":10},"p":{"a":0,"k":[5.71,22.272,0],"ix":2,"l":2},"a":{"a":0,"k":[141.682,57.655,0],"ix":1,"l":2},"s":{"a":0,"k":[100,100,100],"ix":6,"l":2}},"ao":0,"shapes":[{"ty":"gr","it":[{"ind":0,"ty":"sh","ix":1,"ks":{"a":0,"k":{"i":[[0,0],[0,0],[16.942,-4.539],[14.605,-5.337],[0,0],[0,0],[-0.005,-0.017],[-0.004,-0.017],[0,0],[0,0],[-21.6,0],[-40.833,10.941],[2.508,17.767],[0,0]],"o":[[0,0],[-15.316,2.682],[-16.942,4.54],[0,0],[0,0],[0.005,0.017],[0.004,0.016],[0,0],[0,0],[3,7.437],[26.734,0],[73.825,-19.781],[0,0],[0,0]],"v":[[130.726,-57.404],[42.768,-33.837],[-5.904,-22.997],[-53.475,-8.048],[-141.432,15.52],[-133.44,45.348],[-133.426,45.399],[-133.413,45.449],[-133.176,46.33],[-133.12,46.316],[-94.123,57.404],[11.209,40.868],[138.924,-26.579],[138.981,-26.594]],"c":true},"ix":2},"nm":"Path 1","mn":"ADBE Vector Shape - Group","hd":false},{"ind":1,"ty":"sh","ix":2,"ks":{"a":0,"k":{"i":[[0,0],[0,0],[-0.012,-0.081],[22.996,-12.159],[35.55,-9.526],[27.592,0],[2.602,6.45],[0.04,0.067],[0,0],[0,0],[0.027,0.017],[0,0],[0,0],[0,0],[-0.042,0.015],[-16.534,4.431],[-15.686,2.747],[-0.042,0.011]],"o":[[0,0],[-0.001,0.08],[1.103,7.817],[-23.885,12.628],[-39.101,10.477],[-21.298,0],[-0.03,-0.075],[0,0],[0,0],[-0.026,-0.019],[0,0],[0,0],[0,0],[0.043,-0.012],[14.947,-5.462],[16.524,-4.427],[0.043,-0.007],[0,0]],"v":[[129.665,-55.567],[137.424,-26.609],[137.439,-26.368],[102.99,5.063],[10.821,39.419],[-94.122,55.904],[-131.729,45.755],[-131.835,45.541],[-131.967,45.049],[-132.226,45.111],[-132.306,45.055],[-131.991,44.96],[-139.595,16.581],[-53.087,-6.598],[-52.96,-6.639],[-5.516,-21.548],[43.027,-32.359],[43.156,-32.387]],"c":true},"ix":2},"nm":"Path 2","mn":"ADBE Vector Shape - Group","hd":false},{"ty":"mm","mm":1,"nm":"Merge Paths 1","mn":"ADBE Vector Filter - Merge","hd":false},{"ty":"fl","c":{"a":0,"k":[0,0,0,1],"ix":4},"o":{"a":0,"k":100,"ix":5},"r":1,"bm":0,"nm":"Fill 1","mn":"ADBE Vector Graphic - Fill","hd":false},{"ty":"tr","p":{"a":0,"k":[141.682,57.654],"ix":2},"a":{"a":0,"k":[0,0],"ix":1},"s":{"a":0,"k":[100,100],"ix":3},"r":{"a":0,"k":0,"ix":6},"o":{"a":0,"k":100,"ix":7},"sk":{"a":0,"k":0,"ix":4},"sa":{"a":0,"k":0,"ix":5},"nm":"Transform"}],"nm":"Group 1","np":4,"cix":2,"bm":0,"ix":1,"mn":"ADBE Vector Group","hd":false},{"ty":"gr","it":[{"ind":0,"ty":"sh","ix":1,"ks":{"a":0,"k":{"i":[[27.656,0],[2.763,6.849],[0.041,0.053],[0,0],[0,0],[-16.559,4.437],[-15.708,2.751],[0,0],[0,0],[-0.01,-0.067],[72.561,-19.442]],"o":[[-21.937,0],[-0.026,-0.066],[0,0],[0,0],[15.029,-5.489],[16.545,-4.433],[0,0],[0,0],[-0.012,0.065],[2.441,17.29],[-39.159,10.493]],"v":[[-94.177,56.57],[-132.479,45.951],[-132.581,45.771],[-140.568,15.966],[-53.335,-7.408],[-5.764,-22.357],[42.843,-33.182],[130.142,-56.57],[138.13,-26.757],[138.127,-26.557],[10.96,40.059]],"c":true},"ix":2},"nm":"Path 1","mn":"ADBE Vector Shape - Group","hd":false},{"ty":"fl","c":{"a":0,"k":[0.921568687289,1,0,1],"ix":4},"o":{"a":0,"k":100,"ix":5},"r":1,"bm":0,"nm":"Fill 1","mn":"ADBE Vector Graphic - Fill","hd":false},{"ty":"tr","p":{"a":0,"k":[141.736,57.739],"ix":2},"a":{"a":0,"k":[0,0],"ix":1},"s":{"a":0,"k":[100,100],"ix":3},"r":{"a":0,"k":0,"ix":6},"o":{"a":0,"k":100,"ix":7},"sk":{"a":0,"k":0,"ix":4},"sa":{"a":0,"k":0,"ix":5},"nm":"Transform"}],"nm":"Group 2","np":2,"cix":2,"bm":0,"ix":2,"mn":"ADBE Vector Group","hd":false}],"ip":0,"op":151,"st":0,"ct":1,"bm":0},{"ddd":0,"ind":11,"ty":3,"nm":"Null 2","sr":1,"ks":{"o":{"a":0,"k":0,"ix":11},"r":{"a":0,"k":0,"ix":10},"p":{"a":1,"k":[{"i":{"x":0.19,"y":1},"o":{"x":0.81,"y":0},"t":28,"s":[256,256,0],"to":[0,9,0],"ti":[0,0,0]},{"i":{"x":0.19,"y":1},"o":{"x":0.81,"y":0},"t":35,"s":[256,310,0],"to":[0,0,0],"ti":[0,9,0]},{"t":42,"s":[256,256,0]}],"ix":2,"l":2},"a":{"a":0,"k":[0,0,0],"ix":1,"l":2},"s":{"a":1,"k":[{"i":{"x":[0.19,0.19,0.19],"y":[1,1,1]},"o":{"x":[0.81,0.81,0.81],"y":[0,0,0]},"t":28,"s":[100,100,100]},{"i":{"x":[0.19,0.19,0.19],"y":[1,1,1]},"o":{"x":[0.81,0.81,0.81],"y":[0,0,0]},"t":35,"s":[100,77,100]},{"t":42,"s":[100,100,100]}],"ix":6,"l":2}},"ao":0,"ip":0,"op":151,"st":0,"bm":0},{"ddd":0,"ind":12,"ty":4,"nm":"Layer 24 Outlines","parent":11,"sr":1,"ks":{"o":{"a":0,"k":100,"ix":11},"r":{"a":0,"k":0,"ix":10},"p":{"a":0,"k":[10.32,59.638,0],"ix":2,"l":2},"a":{"a":0,"k":[126.1,129.242,0],"ix":1,"l":2},"s":{"a":0,"k":[98.411,98.837,100],"ix":6,"l":2}},"ao":0,"shapes":[{"ty":"gr","it":[{"ind":0,"ty":"sh","ix":1,"ks":{"a":0,"k":{"i":[[0,0],[0,0],[0,0],[0,0]],"o":[[0,0],[0,0],[0,0],[0,0]],"v":[[63.451,-46.231],[72.321,-13.126],[105.427,-21.996],[96.556,-55.101]],"c":true},"ix":2},"nm":"Path 1","mn":"ADBE Vector Shape - Group","hd":false},{"ind":1,"ty":"sh","ix":2,"ks":{"a":0,"k":{"i":[[0,0],[0,0],[0,0],[0,0]],"o":[[0,0],[0,0],[0,0],[0,0]],"v":[[28.897,-36.972],[37.767,-3.867],[70.873,-12.738],[62.002,-45.843]],"c":true},"ix":2},"nm":"Path 2","mn":"ADBE Vector Shape - Group","hd":false},{"ind":2,"ty":"sh","ix":3,"ks":{"a":0,"k":{"i":[[0,0],[0,0],[0,0],[0,0]],"o":[[0,0],[0,0],[0,0],[0,0]],"v":[[-4.217,-28.099],[4.653,5.006],[36.318,-3.479],[27.448,-36.584]],"c":true},"ix":2},"nm":"Path 3","mn":"ADBE Vector Shape - Group","hd":false},{"ind":3,"ty":"sh","ix":4,"ks":{"a":0,"k":{"i":[[0,0],[0,0],[0,0],[0,0]],"o":[[0,0],[0,0],[0,0],[0,0]],"v":[[-38.772,-18.841],[-29.901,14.265],[3.204,5.394],[-5.666,-27.711]],"c":true},"ix":2},"nm":"Path 4","mn":"ADBE Vector Shape - Group","hd":false},{"ind":4,"ty":"sh","ix":5,"ks":{"a":0,"k":{"i":[[0,0],[0,0],[0,0],[0,0]],"o":[[0,0],[0,0],[0,0],[0,0]],"v":[[-73.326,-9.582],[-64.455,23.523],[-31.35,14.653],[-40.22,-18.452]],"c":true},"ix":2},"nm":"Path 5","mn":"ADBE Vector Shape - Group","hd":false},{"ind":5,"ty":"sh","ix":6,"ks":{"a":0,"k":{"i":[[0,0],[0,0],[0,0],[0,0]],"o":[[0,0],[0,0],[0,0],[0,0]],"v":[[-106.44,-0.709],[-97.569,32.396],[-65.904,23.912],[-74.775,-9.194]],"c":true},"ix":2},"nm":"Path 6","mn":"ADBE Vector Shape - Group","hd":false},{"ind":6,"ty":"sh","ix":7,"ks":{"a":0,"k":{"i":[[0,0],[0,0],[0,0],[0,0]],"o":[[0,0],[0,0],[0,0],[0,0]],"v":[[-56.645,58.466],[-65.516,25.361],[-97.181,33.845],[-88.311,66.95]],"c":true},"ix":2},"nm":"Path 7","mn":"ADBE Vector Shape - Group","hd":false},{"ind":7,"ty":"sh","ix":8,"ks":{"a":0,"k":{"i":[[0,0],[0,0],[0,0],[0,0]],"o":[[0,0],[0,0],[0,0],[0,0]],"v":[[-22.091,49.207],[-30.962,16.102],[-64.067,24.972],[-55.196,58.077]],"c":true},"ix":2},"nm":"Path 8","mn":"ADBE Vector Shape - Group","hd":false},{"ind":8,"ty":"sh","ix":9,"ks":{"a":0,"k":{"i":[[0,0],[0,0],[0,0],[0,0]],"o":[[0,0],[0,0],[0,0],[0,0]],"v":[[12.463,39.948],[3.592,6.843],[-29.513,15.714],[-20.642,48.819]],"c":true},"ix":2},"nm":"Path 9","mn":"ADBE Vector Shape - Group","hd":false},{"ind":9,"ty":"sh","ix":10,"ks":{"a":0,"k":{"i":[[0,0],[0,0],[0,0],[0,0]],"o":[[0,0],[0,0],[0,0],[0,0]],"v":[[45.577,31.075],[36.707,-2.03],[5.041,6.455],[13.912,39.56]],"c":true},"ix":2},"nm":"Path 10","mn":"ADBE Vector Shape - Group","hd":false},{"ind":10,"ty":"sh","ix":11,"ks":{"a":0,"k":{"i":[[0,0],[0,0],[0,0],[0,0]],"o":[[0,0],[0,0],[0,0],[0,0]],"v":[[80.131,21.817],[71.261,-11.289],[38.156,-2.418],[47.026,30.687]],"c":true},"ix":2},"nm":"Path 11","mn":"ADBE Vector Shape - Group","hd":false},{"ind":11,"ty":"sh","ix":12,"ks":{"a":0,"k":{"i":[[0,0],[0,0],[0,0],[0,0]],"o":[[0,0],[0,0],[0,0],[0,0]],"v":[[114.685,12.558],[105.815,-20.547],[72.71,-11.677],[81.58,21.428]],"c":true},"ix":2},"nm":"Path 12","mn":"ADBE Vector Shape - Group","hd":false},{"ind":12,"ty":"sh","ix":13,"ks":{"a":0,"k":{"i":[[0,0],[0,0],[0,0],[0,0]],"o":[[0,0],[0,0],[0,0],[0,0]],"v":[[54.578,-79.345],[63.063,-47.68],[96.168,-56.55],[87.683,-88.216]],"c":true},"ix":2},"nm":"Path 13","mn":"ADBE Vector Shape - Group","hd":false},{"ind":13,"ty":"sh","ix":14,"ks":{"a":0,"k":{"i":[[0,0],[0,0],[0,0],[0,0]],"o":[[0,0],[0,0],[0,0],[0,0]],"v":[[20.024,-70.087],[28.509,-38.421],[61.614,-47.292],[53.129,-78.957]],"c":true},"ix":2},"nm":"Path 14","mn":"ADBE Vector Shape - Group","hd":false},{"ind":14,"ty":"sh","ix":15,"ks":{"a":0,"k":{"i":[[0,0],[0,0],[0,0],[0,0]],"o":[[0,0],[0,0],[0,0],[0,0]],"v":[[-13.09,-61.214],[-4.606,-29.548],[27.06,-38.033],[18.575,-69.698]],"c":true},"ix":2},"nm":"Path 15","mn":"ADBE Vector Shape - Group","hd":false},{"ind":15,"ty":"sh","ix":16,"ks":{"a":0,"k":{"i":[[0,0],[0,0],[0,0],[0,0]],"o":[[0,0],[0,0],[0,0],[0,0]],"v":[[-47.645,-51.955],[-39.16,-20.289],[-6.055,-29.16],[-14.539,-60.825]],"c":true},"ix":2},"nm":"Path 16","mn":"ADBE Vector Shape - Group","hd":false},{"ind":16,"ty":"sh","ix":17,"ks":{"a":0,"k":{"i":[[0,0],[0,0],[0,0],[0,0]],"o":[[0,0],[0,0],[0,0],[0,0]],"v":[[-82.199,-42.696],[-73.714,-11.031],[-40.609,-19.901],[-49.093,-51.567]],"c":true},"ix":2},"nm":"Path 17","mn":"ADBE Vector Shape - Group","hd":false},{"ind":17,"ty":"sh","ix":18,"ks":{"a":0,"k":{"i":[[0,0],[0,0],[0,0],[0,0]],"o":[[0,0],[0,0],[0,0],[0,0]],"v":[[-115.313,-33.823],[-106.828,-2.158],[-75.163,-10.642],[-83.647,-42.308]],"c":true},"ix":2},"nm":"Path 18","mn":"ADBE Vector Shape - Group","hd":false},{"ind":18,"ty":"sh","ix":19,"ks":{"a":0,"k":{"i":[[0,0],[0,0],[0,0],[0,0]],"o":[[0,0],[0,0],[0,0],[0,0]],"v":[[-47.772,91.58],[-56.257,59.915],[-87.922,68.399],[-79.438,100.065]],"c":true},"ix":2},"nm":"Path 19","mn":"ADBE Vector Shape - Group","hd":false},{"ind":19,"ty":"sh","ix":20,"ks":{"a":0,"k":{"i":[[0,0],[0,0],[0,0],[0,0]],"o":[[0,0],[0,0],[0,0],[0,0]],"v":[[-13.218,82.321],[-21.703,50.656],[-54.808,59.526],[-46.323,91.192]],"c":true},"ix":2},"nm":"Path 20","mn":"ADBE Vector Shape - Group","hd":false},{"ind":20,"ty":"sh","ix":21,"ks":{"a":0,"k":{"i":[[0,0],[0,0],[0,0],[0,0]],"o":[[0,0],[0,0],[0,0],[0,0]],"v":[[21.336,73.063],[12.851,41.397],[-20.254,50.268],[-11.769,81.933]],"c":true},"ix":2},"nm":"Path 21","mn":"ADBE Vector Shape - Group","hd":false},{"ind":21,"ty":"sh","ix":22,"ks":{"a":0,"k":{"i":[[0,0],[0,0],[0,0],[0,0]],"o":[[0,0],[0,0],[0,0],[0,0]],"v":[[54.45,64.19],[45.965,32.524],[14.3,41.009],[22.785,72.674]],"c":true},"ix":2},"nm":"Path 22","mn":"ADBE Vector Shape - Group","hd":false},{"ind":22,"ty":"sh","ix":23,"ks":{"a":0,"k":{"i":[[0,0],[0,0],[0,0],[0,0]],"o":[[0,0],[0,0],[0,0],[0,0]],"v":[[89.004,54.931],[80.519,23.265],[47.414,32.136],[55.899,63.801]],"c":true},"ix":2},"nm":"Path 23","mn":"ADBE Vector Shape - Group","hd":false},{"ind":23,"ty":"sh","ix":24,"ks":{"a":0,"k":{"i":[[0,0],[0,0],[0,0],[0,0]],"o":[[0,0],[0,0],[0,0],[0,0]],"v":[[10.765,-104.641],[19.636,-71.535],[52.741,-80.406],[43.87,-113.511]],"c":true},"ix":2},"nm":"Path 24","mn":"ADBE Vector Shape - Group","hd":false},{"ind":24,"ty":"sh","ix":25,"ks":{"a":0,"k":{"i":[[0,0],[0,0],[0,0],[0,0]],"o":[[0,0],[0,0],[0,0],[0,0]],"v":[[-22.349,-95.768],[-13.479,-62.662],[18.187,-71.147],[9.316,-104.252]],"c":true},"ix":2},"nm":"Path 25","mn":"ADBE Vector Shape - Group","hd":false},{"ind":25,"ty":"sh","ix":26,"ks":{"a":0,"k":{"i":[[0,0],[0,0],[0,0],[0,0]],"o":[[0,0],[0,0],[0,0],[0,0]],"v":[[-56.903,-86.509],[-48.033,-53.404],[-14.928,-62.274],[-23.798,-95.379]],"c":true},"ix":2},"nm":"Path 26","mn":"ADBE Vector Shape - Group","hd":false},{"ind":26,"ty":"sh","ix":27,"ks":{"a":0,"k":{"i":[[0,0],[0,0],[0,0],[0,0]],"o":[[0,0],[0,0],[0,0],[0,0]],"v":[[-91.457,-77.25],[-82.587,-44.145],[-49.482,-53.016],[-58.352,-86.121]],"c":true},"ix":2},"nm":"Path 27","mn":"ADBE Vector Shape - Group","hd":false},{"ind":27,"ty":"sh","ix":28,"ks":{"a":0,"k":{"i":[[0,0],[0,0],[0,0],[0,0]],"o":[[0,0],[0,0],[0,0],[0,0]],"v":[[-4.345,115.436],[-12.83,83.77],[-45.935,92.641],[-37.45,124.306]],"c":true},"ix":2},"nm":"Path 28","mn":"ADBE Vector Shape - Group","hd":false},{"ind":28,"ty":"sh","ix":29,"ks":{"a":0,"k":{"i":[[0,0],[0,0],[0,0],[0,0]],"o":[[0,0],[0,0],[0,0],[0,0]],"v":[[30.209,106.177],[21.724,74.511],[-11.381,83.382],[-2.896,115.047]],"c":true},"ix":2},"nm":"Path 29","mn":"ADBE Vector Shape - Group","hd":false},{"ind":29,"ty":"sh","ix":30,"ks":{"a":0,"k":{"i":[[0,0],[0,0],[0,0],[0,0]],"o":[[0,0],[0,0],[0,0],[0,0]],"v":[[63.323,97.304],[54.838,65.638],[23.173,74.123],[31.658,105.789]],"c":true},"ix":2},"nm":"Path 30","mn":"ADBE Vector Shape - Group","hd":false},{"ind":30,"ty":"sh","ix":31,"ks":{"a":0,"k":{"i":[[0,0],[0,0],[0,0],[0,0]],"o":[[0,0],[0,0],[0,0],[0,0]],"v":[[97.877,88.045],[89.392,56.38],[56.287,65.25],[64.772,96.916]],"c":true},"ix":2},"nm":"Path 31","mn":"ADBE Vector Shape - Group","hd":false},{"ind":31,"ty":"sh","ix":32,"ks":{"a":0,"k":{"i":[[0,0],[0.559,0.189],[0,0],[0,0],[0,0],[0,0],[0,0],[0,0],[0,0],[0,0],[0,0],[0,0],[0,0],[0,0],[0,0],[0,0],[0,0],[0,0],[0,0],[0,0],[0,0],[0,0],[0,0],[0,0],[0,0],[0,0],[0,0],[0,0],[0,0],[0,0],[0,0],[0,0],[-0.126,-0.129],[-0.248,-0.289],[0,0],[0,0],[-0.559,-0.13],[0,0],[0,0],[0,0],[0,0],[-1.386,-0.143],[0,0],[0,0],[-0.533,-0.048],[0,0],[0,0],[0,0],[-0.314,0],[0,0],[0,0],[0,0],[0,0],[-0.504,0.046],[0,0],[0,0],[0,0],[-0.486,0.107],[0,0],[0,0],[0,0],[-0.363,0.425],[0,0],[0,0],[0,0],[0,0],[0,0],[0,0],[0,0],[0,0],[0,0],[0,0],[0,0],[0,0],[0,0],[0,0],[0,0],[0,0],[0,0],[0,0],[0,0],[0,0],[0,0],[0,0],[0,0],[0,0],[0,0],[0,0],[0,0],[0,0],[0,0],[0.475,-0.193],[0,0],[0,0],[0,0],[0.496,-0.09],[0,0],[0,0],[0,0],[0,0],[3.004,-0.249],[0,0],[0,0],[0.516,-0.007],[0,0],[0,0],[0,0],[0.524,0.028],[0,0],[0,0],[0,0],[0.536,0.076],[0,0],[0,0],[0,0],[0,0],[1.19,0.2],[0,0]],"o":[[-0.577,-0.186],[0,0],[0,0],[0,0],[0,0],[0,0],[0,0],[0,0],[0,0],[0,0],[0,0],[0,0],[0,0],[0,0],[0,0],[0,0],[0,0],[0,0],[0,0],[0,0],[0,0],[0,0],[0,0],[0,0],[0,0],[0,0],[0,0],[0,0],[0,0],[0,0],[0,0],[0.117,0.138],[0.208,0.292],[0,0],[0,0],[0.547,0.133],[0,0],[0,0],[0,0],[0,0],[1.355,0.157],[0,0],[0,0],[0.529,0.05],[0,0],[0,0],[0,0],[0.313,0.001],[0,0],[0,0],[0,0],[0,0],[0.508,-0.043],[0,0],[0,0],[0,0],[0.494,-0.104],[0,0],[0,0],[0,0],[0.446,-0.417],[0,0],[0,0],[0,0],[0,0],[0,0],[0,0],[0,0],[0,0],[0,0],[0,0],[0,0],[0,0],[0,0],[0,0],[0,0],[0,0],[0,0],[0,0],[0,0],[0,0],[0,0],[0,0],[0,0],[0,0],[0,0],[0,0],[0,0],[0,0],[0,0],[-0.457,0.196],[0,0],[0,0],[0,0],[-0.491,0.092],[0,0],[0,0],[0,0],[0,0],[-2.898,0.298],[0,0],[0,0],[-0.515,0.007],[0,0],[0,0],[0,0],[-0.526,-0.027],[0,0],[0,0],[0,0],[-0.54,-0.075],[0,0],[0,0],[0,0],[0,0],[-1.22,-0.19],[0,0],[0,0]],"v":[[-104.427,-125.655],[-106.131,-126.217],[-102.167,-111.425],[-125.85,-105.079],[-125.714,-103.563],[-101.779,-109.976],[-93.294,-78.311],[-122.75,-70.418],[-122.615,-68.902],[-92.906,-76.862],[-84.036,-43.757],[-115.701,-35.272],[-121.564,-57.152],[-120.786,-48.453],[-117.15,-34.884],[-119.516,-34.25],[-119.38,-32.733],[-116.762,-33.435],[-108.277,-1.77],[-116.416,0.411],[-116.28,1.928],[-107.889,-0.321],[-99.018,32.785],[-113.181,36.58],[-113.046,38.096],[-98.63,34.233],[-89.76,67.339],[-109.947,72.748],[-109.811,74.264],[-89.371,68.788],[-80.887,100.453],[-105.416,107.026],[-105.051,107.427],[-104.368,108.298],[-80.498,101.902],[-75.281,121.375],[-73.622,121.77],[-79.05,101.514],[-47.384,93.029],[-38.899,124.694],[-45.579,126.484],[-41.466,126.935],[-38.511,126.143],[-38.213,127.256],[-36.621,127.402],[-37.062,125.755],[-3.957,116.884],[-0.713,128.991],[0.227,128.992],[0.84,128.992],[-2.508,116.496],[30.597,107.626],[35.923,127.503],[37.44,127.369],[32.046,107.238],[63.711,98.753],[70.114,122.649],[71.583,122.333],[65.16,98.365],[98.265,89.494],[103.635,109.532],[104.849,108.268],[99.714,89.106],[109.165,86.574],[109.307,84.983],[99.326,87.657],[90.841,55.992],[112.417,50.21],[112.559,48.619],[90.453,54.543],[81.968,22.877],[115.074,14.007],[115.509,15.632],[115.898,11.287],[107.264,-20.936],[119.062,-24.097],[119.204,-25.688],[106.875,-22.385],[98.005,-55.49],[122.455,-62.041],[122.598,-63.632],[97.617,-56.939],[89.132,-88.604],[120.797,-97.089],[124.391,-83.679],[124.779,-88.024],[122.246,-97.477],[125.707,-98.404],[125.85,-99.995],[121.858,-98.926],[113.802,-128.992],[112.405,-128.408],[120.409,-98.538],[88.744,-90.053],[80.783,-119.764],[79.303,-119.491],[87.295,-89.665],[54.19,-80.794],[45.319,-113.899],[51.928,-115.67],[43.073,-114.85],[10.377,-106.09],[8.472,-113.199],[6.925,-113.178],[8.928,-105.701],[-22.737,-97.217],[-27.186,-113.82],[-28.761,-113.902],[-24.186,-96.828],[-57.291,-87.958],[-65.153,-117.298],[-66.767,-117.524],[-58.74,-87.57],[-91.846,-78.699],[-100.33,-110.365],[-71.164,-118.18],[-74.779,-118.764],[-100.718,-111.813]],"c":true},"ix":2},"nm":"Path 32","mn":"ADBE Vector Shape - Group","hd":false},{"ty":"mm","mm":1,"nm":"Merge Paths 1","mn":"ADBE Vector Filter - Merge","hd":false},{"ty":"st","c":{"a":0,"k":[0,0,0,1],"ix":3},"o":{"a":0,"k":100,"ix":4},"w":{"a":0,"k":2,"ix":5},"lc":2,"lj":2,"bm":0,"nm":"Stroke 1","mn":"ADBE Vector Graphic - Stroke","hd":false},{"ty":"tr","p":{"a":0,"k":[126.1,129.242],"ix":2},"a":{"a":0,"k":[0,0],"ix":1},"s":{"a":0,"k":[100,100],"ix":3},"r":{"a":0,"k":0,"ix":6},"o":{"a":0,"k":100,"ix":7},"sk":{"a":0,"k":0,"ix":4},"sa":{"a":0,"k":0,"ix":5},"nm":"Transform"}],"nm":"Group 1","np":34,"cix":2,"bm":0,"ix":1,"mn":"ADBE Vector Group","hd":false}],"ip":0,"op":151,"st":0,"ct":1,"bm":0},{"ddd":0,"ind":13,"ty":4,"nm":"Layer 26 Outlines","parent":11,"sr":1,"ks":{"o":{"a":0,"k":100,"ix":11},"r":{"a":1,"k":[{"i":{"x":[0],"y":[1]},"o":{"x":[1],"y":[0]},"t":29,"s":[0]},{"i":{"x":[0],"y":[1]},"o":{"x":[1],"y":[0]},"t":34,"s":[24]},{"t":41,"s":[0]}],"ix":10},"p":{"a":1,"k":[{"i":{"x":0,"y":1},"o":{"x":1,"y":0},"t":29,"s":[14.344,125.228,0],"to":[0,-13,0],"ti":[0,0,0]},{"i":{"x":0,"y":1},"o":{"x":1,"y":0},"t":34,"s":[14.344,47.228,0],"to":[0,0,0],"ti":[0,-13,0]},{"t":41,"s":[14.344,125.228,0]}],"ix":2,"l":2},"a":{"a":0,"k":[78.594,38.478,0],"ix":1,"l":2},"s":{"a":1,"k":[{"i":{"x":[0,0,0],"y":[1,1,1]},"o":{"x":[1,1,1],"y":[0,0,0]},"t":29,"s":[100,100,100]},{"i":{"x":[0,0,0],"y":[1,1,1]},"o":{"x":[1,1,1],"y":[0,0,0]},"t":34,"s":[100,216,100]},{"t":41,"s":[100,100,100]}],"ix":6,"l":2}},"ao":0,"shapes":[{"ty":"gr","it":[{"ind":0,"ty":"sh","ix":1,"ks":{"a":0,"k":{"i":[[0,0],[0,0],[0,0],[0,0],[0,0],[0,0],[0,0],[0,0],[0,0],[0,0],[0,0],[0,0]],"o":[[0,0],[0,0],[0,0],[0,0],[0,0],[0,0],[0,0],[0,0],[0,0],[0,0],[0,0],[0,0]],"v":[[38.078,38.228],[-45.117,38.228],[-45.283,34.622],[-78.344,7.169],[-36.243,17.565],[-41.022,-29.32],[-18.851,1.105],[0.898,-28.835],[4.111,2.695],[46.371,-38.228],[28.886,20.029],[78.344,25.332]],"c":true},"ix":2},"nm":"Path 1","mn":"ADBE Vector Shape - Group","hd":false},{"ty":"st","c":{"a":0,"k":[0,0,0,1],"ix":3},"o":{"a":0,"k":100,"ix":4},"w":{"a":0,"k":1.5,"ix":5},"lc":1,"lj":1,"ml":4,"bm":0,"nm":"Stroke 1","mn":"ADBE Vector Graphic - Stroke","hd":false},{"ty":"fl","c":{"a":0,"k":[0.921568687289,1,0,1],"ix":4},"o":{"a":0,"k":100,"ix":5},"r":1,"bm":0,"nm":"Fill 1","mn":"ADBE Vector Graphic - Fill","hd":false},{"ty":"tr","p":{"a":0,"k":[78.594,38.478],"ix":2},"a":{"a":0,"k":[0,0],"ix":1},"s":{"a":0,"k":[100,100],"ix":3},"r":{"a":0,"k":0,"ix":6},"o":{"a":0,"k":100,"ix":7},"sk":{"a":0,"k":0,"ix":4},"sa":{"a":0,"k":0,"ix":5},"nm":"Transform"}],"nm":"Group 1","np":3,"cix":2,"bm":0,"ix":1,"mn":"ADBE Vector Group","hd":false}],"ip":0,"op":151,"st":0,"ct":1,"bm":0},{"ddd":0,"ind":14,"ty":4,"nm":"Layer 28 Outlines","parent":11,"sr":1,"ks":{"o":{"a":0,"k":100,"ix":11},"r":{"a":0,"k":0,"ix":10},"p":{"a":0,"k":[10.546,-90.518,0],"ix":2,"l":2},"a":{"a":0,"k":[129.434,23.625,0],"ix":1,"l":2},"s":{"a":0,"k":[100,100,100],"ix":6,"l":2}},"ao":0,"shapes":[{"ty":"gr","it":[{"ind":0,"ty":"sh","ix":1,"ks":{"a":0,"k":{"i":[[-23.014,-8.338],[0,6.063],[71.346,0],[0,-16.735],[-13.074,-4.737],[-45.499,0]],"o":[[13.074,-4.737],[0,-16.735],[-71.346,0],[0,6.063],[23.014,-8.338],[45.499,0]],"v":[[108.52,23.374],[129.184,6.928],[0.001,-23.374],[-129.183,6.928],[-108.518,23.374],[0.001,9.519]],"c":true},"ix":2},"nm":"Path 1","mn":"ADBE Vector Shape - Group","hd":false},{"ty":"fl","c":{"a":0,"k":[0,0,0,1],"ix":4},"o":{"a":0,"k":100,"ix":5},"r":1,"bm":0,"nm":"Fill 1","mn":"ADBE Vector Graphic - Fill","hd":false},{"ty":"tr","p":{"a":0,"k":[129.434,23.624],"ix":2},"a":{"a":0,"k":[0,0],"ix":1},"s":{"a":0,"k":[100,100],"ix":3},"r":{"a":0,"k":0,"ix":6},"o":{"a":0,"k":100,"ix":7},"sk":{"a":0,"k":0,"ix":4},"sa":{"a":0,"k":0,"ix":5},"nm":"Transform"}],"nm":"Group 1","np":2,"cix":2,"bm":0,"ix":1,"mn":"ADBE Vector Group","hd":false}],"ip":0,"op":151,"st":0,"ct":1,"bm":0},{"ddd":0,"ind":15,"ty":4,"nm":"Layer 29 Outlines","parent":11,"sr":1,"ks":{"o":{"a":0,"k":100,"ix":11},"r":{"a":0,"k":0,"ix":10},"p":{"a":0,"k":[10.5,-83.5,0],"ix":2,"l":2},"a":{"a":0,"k":[130.25,31.25,0],"ix":1,"l":2},"s":{"a":0,"k":[100,100,100],"ix":6,"l":2}},"ao":0,"shapes":[{"ty":"gr","it":[{"ind":0,"ty":"sh","ix":1,"ks":{"a":0,"k":{"i":[[0,-3.76],[6.53,-3.636],[11.688,-2.753],[35.72,0],[23.363,5.502],[6.466,3.6],[0,3.76],[-6.53,3.636],[-11.688,2.753],[-35.72,0],[-23.363,-5.502],[-6.466,-3.6]],"o":[[0,3.76],[-6.466,3.6],[-23.363,5.502],[-35.72,0],[-11.688,-2.753],[-6.53,-3.636],[0,-3.76],[6.466,-3.6],[23.363,-5.502],[35.72,0],[11.688,2.753],[6.53,3.636]],"v":[[128.75,0],[118.958,11.217],[91.398,20.837],[0,29.75],[-91.398,20.837],[-118.958,11.217],[-128.75,0],[-118.958,-11.217],[-91.398,-20.837],[0,-29.75],[91.398,-20.837],[118.958,-11.217]],"c":true},"ix":2},"nm":"Path 1","mn":"ADBE Vector Shape - Group","hd":false},{"ty":"st","c":{"a":0,"k":[0,0,0,1],"ix":3},"o":{"a":0,"k":100,"ix":4},"w":{"a":0,"k":1.5,"ix":5},"lc":1,"lj":1,"ml":4,"bm":0,"nm":"Stroke 1","mn":"ADBE Vector Graphic - Stroke","hd":false},{"ty":"tr","p":{"a":0,"k":[130.25,31.25],"ix":2},"a":{"a":0,"k":[0,0],"ix":1},"s":{"a":0,"k":[100,100],"ix":3},"r":{"a":0,"k":0,"ix":6},"o":{"a":0,"k":100,"ix":7},"sk":{"a":0,"k":0,"ix":4},"sa":{"a":0,"k":0,"ix":5},"nm":"Transform"}],"nm":"Group 1","np":2,"cix":2,"bm":0,"ix":1,"mn":"ADBE Vector Group","hd":false}],"ip":0,"op":151,"st":0,"ct":1,"bm":0},{"ddd":0,"ind":16,"ty":4,"nm":"Layer 30 Outlines","parent":11,"sr":1,"ks":{"o":{"a":0,"k":100,"ix":11},"r":{"a":0,"k":0,"ix":10},"p":{"a":0,"k":[10.547,163.081,0],"ix":2,"l":2},"a":{"a":0,"k":[107.606,26.799,0],"ix":1,"l":2},"s":{"a":0,"k":[100,100,100],"ix":6,"l":2}},"ao":0,"shapes":[{"ty":"gr","it":[{"ind":0,"ty":"sh","ix":1,"ks":{"a":0,"k":{"i":[[0,-3.159],[5.374,-3.098],[9.637,-2.35],[29.466,0],[19.264,4.696],[5.319,3.065],[0,3.158],[-5.375,3.098],[-9.637,2.349],[-29.466,0],[-19.264,-4.696],[-5.319,-3.066]],"o":[[0,3.158],[-5.319,3.065],[-19.264,4.696],[-29.466,0],[-9.637,-2.35],[-5.375,-3.098],[0,-3.159],[5.319,-3.066],[19.264,-4.696],[29.466,0],[9.637,2.349],[5.374,3.098]],"v":[[106.106,0],[98.084,9.49],[75.381,17.691],[0,25.299],[-75.381,17.691],[-98.084,9.49],[-106.106,0],[-98.084,-9.49],[-75.381,-17.691],[0,-25.299],[75.381,-17.691],[98.084,-9.49]],"c":true},"ix":2},"nm":"Path 1","mn":"ADBE Vector Shape - Group","hd":false},{"ty":"st","c":{"a":0,"k":[0,0,0,1],"ix":3},"o":{"a":0,"k":100,"ix":4},"w":{"a":0,"k":1.5,"ix":5},"lc":1,"lj":1,"ml":4,"bm":0,"nm":"Stroke 1","mn":"ADBE Vector Graphic - Stroke","hd":false},{"ty":"fl","c":{"a":0,"k":[0,0,0,1],"ix":4},"o":{"a":0,"k":100,"ix":5},"r":1,"bm":0,"nm":"Fill 1","mn":"ADBE Vector Graphic - Fill","hd":false},{"ty":"tr","p":{"a":0,"k":[107.606,26.799],"ix":2},"a":{"a":0,"k":[0,0],"ix":1},"s":{"a":0,"k":[100,100],"ix":3},"r":{"a":0,"k":0,"ix":6},"o":{"a":0,"k":100,"ix":7},"sk":{"a":0,"k":0,"ix":4},"sa":{"a":0,"k":0,"ix":5},"nm":"Transform"}],"nm":"Group 1","np":3,"cix":2,"bm":0,"ix":1,"mn":"ADBE Vector Group","hd":false}],"ip":0,"op":151,"st":0,"ct":1,"bm":0},{"ddd":0,"ind":17,"ty":4,"nm":"Layer 32 Outlines 2","parent":11,"sr":1,"ks":{"o":{"a":0,"k":100,"ix":11},"r":{"a":0,"k":0,"ix":10},"p":{"a":0,"k":[10.547,48.783,0],"ix":2,"l":2},"a":{"a":0,"k":[130.136,140.598,0],"ix":1,"l":2},"s":{"a":0,"k":[100,100,100],"ix":6,"l":2}},"ao":0,"shapes":[{"ty":"gr","it":[{"ind":0,"ty":"sh","ix":1,"ks":{"a":0,"k":{"i":[[4.7,0],[0,0],[-0.418,-4.681],[0,0],[-1.239,-1.275],[-52.742,0],[-8.718,12.25],[-0.169,1.895],[0,0]],"o":[[0,0],[-4.699,0],[0,0],[0.169,1.895],[8.719,12.25],[52.742,0],[1.239,-1.275],[0,0],[0.418,-4.681]],"v":[[121.499,-140.348],[-121.5,-140.348],[-129.468,-131.635],[-107.507,113.921],[-105.278,118.783],[0,140.348],[105.278,118.783],[107.507,113.921],[129.468,-131.635]],"c":true},"ix":2},"nm":"Path 1","mn":"ADBE Vector Shape - Group","hd":false},{"ind":1,"ty":"sh","ix":2,"ks":{"a":0,"k":{"i":[[0,0],[-1.246,-1.363],[0.164,-1.839],[0,0],[1.036,-1.066],[0.044,-0.062],[50.828,0],[8.495,11.935],[0.053,0.054],[0.132,1.482],[0,0],[-1.246,1.362],[-1.846,0]],"o":[[1.847,0],[1.246,1.363],[0,0],[-0.132,1.481],[-0.053,0.054],[-8.494,11.935],[-50.827,0],[-0.044,-0.062],[-1.036,-1.066],[0,0],[-0.164,-1.84],[1.246,-1.363],[0,0]],"v":[[121.499,-138.848],[126.296,-136.734],[127.974,-131.77],[106.013,113.788],[104.202,117.737],[104.056,117.913],[0,138.848],[-104.056,117.913],[-104.202,117.737],[-106.013,113.787],[-127.974,-131.768],[-126.296,-136.734],[-121.5,-138.848]],"c":true},"ix":2},"nm":"Path 2","mn":"ADBE Vector Shape - Group","hd":false},{"ty":"mm","mm":1,"nm":"Merge Paths 1","mn":"ADBE Vector Filter - Merge","hd":false},{"ty":"fl","c":{"a":0,"k":[0,0,0,1],"ix":4},"o":{"a":0,"k":100,"ix":5},"r":1,"bm":0,"nm":"Fill 1","mn":"ADBE Vector Graphic - Fill","hd":false},{"ty":"tr","p":{"a":0,"k":[130.136,140.598],"ix":2},"a":{"a":0,"k":[0,0],"ix":1},"s":{"a":0,"k":[100,100],"ix":3},"r":{"a":0,"k":0,"ix":6},"o":{"a":0,"k":100,"ix":7},"sk":{"a":0,"k":0,"ix":4},"sa":{"a":0,"k":0,"ix":5},"nm":"Transform"}],"nm":"Group 1","np":4,"cix":2,"bm":0,"ix":1,"mn":"ADBE Vector Group","hd":false},{"ty":"gr","it":[{"ind":0,"ty":"sh","ix":1,"ks":{"a":0,"k":{"i":[[51.049,0],[8.622,12.114],[0.027,0.027],[0.148,1.651],[0,0],[-1.37,1.498],[-2.029,0],[0,0],[-1.371,-1.498],[0.18,-2.022],[0,0],[1.156,-1.188],[0.022,-0.031]],"o":[[-51.048,0],[-0.022,-0.031],[-1.155,-1.189],[0,0],[-0.18,-2.022],[1.37,-1.498],[0,0],[2.03,0],[1.369,1.498],[0,0],[-0.148,1.652],[-0.026,0.027],[-8.621,12.114]],"v":[[0,139.598],[-104.667,118.349],[-104.74,118.261],[-106.76,113.856],[-128.721,-131.702],[-126.849,-137.241],[-121.5,-139.598],[121.499,-139.598],[126.85,-137.241],[128.721,-131.702],[106.76,113.856],[104.74,118.261],[104.667,118.349]],"c":true},"ix":2},"nm":"Path 1","mn":"ADBE Vector Shape - Group","hd":false},{"ty":"fl","c":{"a":0,"k":[0,0.878431432387,1,1],"ix":4},"o":{"a":0,"k":100,"ix":5},"r":1,"bm":0,"nm":"Fill 1","mn":"ADBE Vector Graphic - Fill","hd":false},{"ty":"tr","p":{"a":0,"k":[130.136,140.597],"ix":2},"a":{"a":0,"k":[0,0],"ix":1},"s":{"a":0,"k":[100,100],"ix":3},"r":{"a":0,"k":0,"ix":6},"o":{"a":0,"k":100,"ix":7},"sk":{"a":0,"k":0,"ix":4},"sa":{"a":0,"k":0,"ix":5},"nm":"Transform"}],"nm":"Group 2","np":2,"cix":2,"bm":0,"ix":2,"mn":"ADBE Vector Group","hd":false}],"ip":0,"op":151,"st":0,"ct":1,"bm":0},{"ddd":0,"ind":18,"ty":4,"nm":"Layer 29 Outlines 2","parent":11,"sr":1,"ks":{"o":{"a":0,"k":100,"ix":11},"r":{"a":0,"k":0,"ix":10},"p":{"a":0,"k":[10.5,-83.5,0],"ix":2,"l":2},"a":{"a":0,"k":[130.25,31.25,0],"ix":1,"l":2},"s":{"a":0,"k":[100,100,100],"ix":6,"l":2}},"ao":0,"shapes":[{"ty":"gr","it":[{"ind":0,"ty":"sh","ix":1,"ks":{"a":0,"k":{"i":[[0,-3.76],[6.53,-3.636],[11.688,-2.753],[35.72,0],[23.363,5.502],[6.466,3.6],[0,3.76],[-6.53,3.636],[-11.688,2.753],[-35.72,0],[-23.363,-5.502],[-6.466,-3.6]],"o":[[0,3.76],[-6.466,3.6],[-23.363,5.502],[-35.72,0],[-11.688,-2.753],[-6.53,-3.636],[0,-3.76],[6.466,-3.6],[23.363,-5.502],[35.72,0],[11.688,2.753],[6.53,3.636]],"v":[[128.75,0],[118.958,11.217],[91.398,20.837],[0,29.75],[-91.398,20.837],[-118.958,11.217],[-128.75,0],[-118.958,-11.217],[-91.398,-20.837],[0,-29.75],[91.398,-20.837],[118.958,-11.217]],"c":true},"ix":2},"nm":"Path 1","mn":"ADBE Vector Shape - Group","hd":false},{"ty":"st","c":{"a":0,"k":[1,1,1,1],"ix":3},"o":{"a":0,"k":100,"ix":4},"w":{"a":0,"k":26,"ix":5},"lc":1,"lj":1,"ml":4,"bm":0,"nm":"Stroke 1","mn":"ADBE Vector Graphic - Stroke","hd":false},{"ty":"tr","p":{"a":0,"k":[130.25,31.25],"ix":2},"a":{"a":0,"k":[0,0],"ix":1},"s":{"a":0,"k":[100,100],"ix":3},"r":{"a":0,"k":0,"ix":6},"o":{"a":0,"k":100,"ix":7},"sk":{"a":0,"k":0,"ix":4},"sa":{"a":0,"k":0,"ix":5},"nm":"Transform"}],"nm":"Group 1","np":2,"cix":2,"bm":0,"ix":1,"mn":"ADBE Vector Group","hd":false}],"ip":0,"op":151,"st":0,"ct":1,"bm":0},{"ddd":0,"ind":19,"ty":4,"nm":"Layer 32 Outlines 3","parent":11,"sr":1,"ks":{"o":{"a":0,"k":100,"ix":11},"r":{"a":0,"k":0,"ix":10},"p":{"a":0,"k":[10.547,48.783,0],"ix":2,"l":2},"a":{"a":0,"k":[130.136,140.598,0],"ix":1,"l":2},"s":{"a":0,"k":[100,100,100],"ix":6,"l":2}},"ao":0,"shapes":[{"ty":"gr","it":[{"ind":0,"ty":"sh","ix":1,"ks":{"a":0,"k":{"i":[[51.049,0],[8.622,12.114],[0.027,0.027],[0.148,1.651],[0,0],[-1.37,1.498],[-2.029,0],[0,0],[-1.371,-1.498],[0.18,-2.022],[0,0],[1.156,-1.188],[0.022,-0.031]],"o":[[-51.048,0],[-0.022,-0.031],[-1.155,-1.189],[0,0],[-0.18,-2.022],[1.37,-1.498],[0,0],[2.03,0],[1.369,1.498],[0,0],[-0.148,1.652],[-0.026,0.027],[-8.621,12.114]],"v":[[0,139.598],[-104.667,118.349],[-104.74,118.261],[-106.76,113.856],[-128.721,-131.702],[-126.849,-137.241],[-121.5,-139.598],[121.499,-139.598],[126.85,-137.241],[128.721,-131.702],[106.76,113.856],[104.74,118.261],[104.667,118.349]],"c":true},"ix":2},"nm":"Path 1","mn":"ADBE Vector Shape - Group","hd":false},{"ty":"st","c":{"a":0,"k":[1,1,1,1],"ix":3},"o":{"a":0,"k":100,"ix":4},"w":{"a":0,"k":26,"ix":5},"lc":1,"lj":1,"ml":4,"bm":0,"nm":"Stroke 1","mn":"ADBE Vector Graphic - Stroke","hd":false},{"ty":"fl","c":{"a":0,"k":[1,1,1,1],"ix":4},"o":{"a":0,"k":100,"ix":5},"r":1,"bm":0,"nm":"Fill 1","mn":"ADBE Vector Graphic - Fill","hd":false},{"ty":"tr","p":{"a":0,"k":[130.136,140.597],"ix":2},"a":{"a":0,"k":[0,0],"ix":1},"s":{"a":0,"k":[100,100],"ix":3},"r":{"a":0,"k":0,"ix":6},"o":{"a":0,"k":100,"ix":7},"sk":{"a":0,"k":0,"ix":4},"sa":{"a":0,"k":0,"ix":5},"nm":"Transform"}],"nm":"Group 2","np":3,"cix":2,"bm":0,"ix":1,"mn":"ADBE Vector Group","hd":false}],"ip":0,"op":151,"st":0,"ct":1,"bm":0},{"ddd":0,"ind":20,"ty":4,"nm":"Layer 19 Outlines 2","parent":3,"sr":1,"ks":{"o":{"a":0,"k":100,"ix":11},"r":{"a":0,"k":0,"ix":10},"p":{"a":0,"k":[0.356,1.33,0],"ix":2,"l":2},"a":{"a":0,"k":[137.383,49.464,0],"ix":1,"l":2},"s":{"a":0,"k":[100,100,100],"ix":6,"l":2}},"ao":0,"shapes":[{"ty":"gr","it":[{"ind":0,"ty":"sh","ix":1,"ks":{"a":0,"k":{"i":[[-0.529,-1.974],[1.203,-2.447],[2.897,-2.793],[11.514,-6.166],[37.539,-10.058],[26.096,-0.835],[7.81,1.94],[2.27,1.521],[0.529,1.974],[-1.202,2.447],[-2.898,2.793],[-11.514,6.166],[-37.539,10.058],[-26.097,0.834],[-7.81,-1.94],[-2.27,-1.521]],"o":[[0.529,1.975],[-1.205,2.452],[-5.794,5.585],[-23.017,12.326],[-37.538,10.059],[-13.055,0.418],[-3.905,-0.97],[-2.264,-1.517],[-0.529,-1.975],[1.206,-2.452],[5.793,-5.585],[23.018,-12.325],[37.539,-10.059],[13.054,-0.418],[3.906,0.97],[2.265,1.518]],"v":[[135.354,-36.268],[134.361,-29.635],[128.185,-21.745],[101.9,-3.931],[8.337,31.113],[-90.213,47.546],[-121.883,45.262],[-131.178,41.514],[-135.355,36.269],[-134.36,29.635],[-128.184,21.745],[-101.9,3.932],[-8.336,-31.112],[90.214,-47.546],[121.883,-45.262],[131.177,-41.516]],"c":true},"ix":2},"nm":"Path 1","mn":"ADBE Vector Shape - Group","hd":false},{"ty":"st","c":{"a":0,"k":[1,1,1,1],"ix":3},"o":{"a":0,"k":100,"ix":4},"w":{"a":0,"k":26,"ix":5},"lc":1,"lj":1,"ml":4,"bm":0,"nm":"Stroke 1","mn":"ADBE Vector Graphic - Stroke","hd":false},{"ty":"fl","c":{"a":0,"k":[1,1,1,1],"ix":4},"o":{"a":0,"k":100,"ix":5},"r":1,"bm":0,"nm":"Fill 1","mn":"ADBE Vector Graphic - Fill","hd":false},{"ty":"tr","p":{"a":0,"k":[137.383,49.464],"ix":2},"a":{"a":0,"k":[0,0],"ix":1},"s":{"a":0,"k":[100,100],"ix":3},"r":{"a":0,"k":0,"ix":6},"o":{"a":0,"k":100,"ix":7},"sk":{"a":0,"k":0,"ix":4},"sa":{"a":0,"k":0,"ix":5},"nm":"Transform"}],"nm":"Group 1","np":3,"cix":2,"bm":0,"ix":1,"mn":"ADBE Vector Group","hd":false}],"ip":0,"op":151,"st":0,"ct":1,"bm":0},{"ddd":0,"ind":21,"ty":4,"nm":"Layer 21 Outlines 2","parent":3,"sr":1,"ks":{"o":{"a":0,"k":100,"ix":11},"r":{"a":0,"k":0,"ix":10},"p":{"a":0,"k":[5.71,22.272,0],"ix":2,"l":2},"a":{"a":0,"k":[141.682,57.655,0],"ix":1,"l":2},"s":{"a":0,"k":[100,100,100],"ix":6,"l":2}},"ao":0,"shapes":[{"ty":"gr","it":[{"ind":0,"ty":"sh","ix":1,"ks":{"a":0,"k":{"i":[[27.656,0],[2.763,6.849],[0.041,0.053],[0,0],[0,0],[-16.559,4.437],[-15.708,2.751],[0,0],[0,0],[-0.01,-0.067],[72.561,-19.442]],"o":[[-21.937,0],[-0.026,-0.066],[0,0],[0,0],[15.029,-5.489],[16.545,-4.433],[0,0],[0,0],[-0.012,0.065],[2.441,17.29],[-39.159,10.493]],"v":[[-94.177,56.57],[-132.479,45.951],[-132.581,45.771],[-140.568,15.966],[-53.335,-7.408],[-5.764,-22.357],[42.843,-33.182],[130.142,-56.57],[138.13,-26.757],[138.127,-26.557],[10.96,40.059]],"c":true},"ix":2},"nm":"Path 1","mn":"ADBE Vector Shape - Group","hd":false},{"ty":"st","c":{"a":0,"k":[1,1,1,1],"ix":3},"o":{"a":0,"k":100,"ix":4},"w":{"a":0,"k":26,"ix":5},"lc":2,"lj":2,"bm":0,"nm":"Stroke 1","mn":"ADBE Vector Graphic - Stroke","hd":false},{"ty":"fl","c":{"a":0,"k":[1,1,1,1],"ix":4},"o":{"a":0,"k":100,"ix":5},"r":1,"bm":0,"nm":"Fill 1","mn":"ADBE Vector Graphic - Fill","hd":false},{"ty":"tr","p":{"a":0,"k":[141.736,57.739],"ix":2},"a":{"a":0,"k":[0,0],"ix":1},"s":{"a":0,"k":[100,100],"ix":3},"r":{"a":0,"k":0,"ix":6},"o":{"a":0,"k":100,"ix":7},"sk":{"a":0,"k":0,"ix":4},"sa":{"a":0,"k":0,"ix":5},"nm":"Transform"}],"nm":"Group 2","np":3,"cix":2,"bm":0,"ix":1,"mn":"ADBE Vector Group","hd":false}],"ip":0,"op":151,"st":0,"ct":1,"bm":0}],"markers":[],"props":{}}